django_boto-0.3.8.dist-info/METADATA
django_boto-0.3.8.dist-info/top_level.txt
django_boto-0.3.8.dist-info/RECORD
django_boto-0.3.8.dist-info/metadata.json
django_boto-0.3.8.dist-info/DESCRIPTION.rst
django_boto-0.3.8.dist-info/WHEEL
django_boto/tests.py
django_boto/__init__.py
django_boto/models.py
django_boto/settings.py
django_boto/s3/storage.py
django_boto/s3/__init__.py
django_boto/s3/shortcuts.py
