Metadata-Version: 2.0
Name: django-boto
Version: 0.3.8
Summary: Wrapper of boto package for django
Home-page: https://github.com/qnub/django-boto/
Author: Vadim Lopatyuk
Author-email: qnub.ru@gmail.com
License: MIT
Platform: Posix; MacOS X; Windows
Classifier: Development Status :: 4 - Beta
Classifier: Intended Audience :: Developers
Classifier: License :: OSI Approved :: MIT License
Classifier: Operating System :: OS Independent
Classifier: Topic :: Internet
Classifier: Programming Language :: Python :: 2
Classifier: Programming Language :: Python :: 2.5
Classifier: Programming Language :: Python :: 2.6
Classifier: Programming Language :: Python :: 2.7
Classifier: Framework :: Django
Requires-Dist: django (>=1.3)
Requires-Dist: boto (>=2.3.0)
